vimdatautils/__init__.py
vimdatautils/dal.py
vimdatautils/inbound_pipeline.py
vimdatautils/s3_utility.py
vimdatautils/resources/create_inbound_stored_functions.sql
vimdatautils/resources/update_log_table.sql
vimdatautils-0.79.dist-info/METADATA
vimdatautils-0.79.dist-info/WHEEL
vimdatautils-0.79.dist-info/top_level.txt
vimdatautils-0.79.dist-info/RECORD
