Metadata-Version: 2.1
Name: vimdatautils
Version: 0.79
Summary: Vim pipeline utility to ingest data
Home-page: UNKNOWN
Author: Vim D&I
Author-email: dni@getvim.com
License: UNKNOWN
Platform: UNKNOWN
Classifier: Programming Language :: Python :: 3
Classifier: Operating System :: OS Independent
Classifier: Topic :: Database
Requires-Python: >=3
Requires-Dist: credstash (==1.15.0)
Requires-Dist: jinja2 (==2.10.1)
Requires-Dist: psycopg2 (==2.8.3)
Requires-Dist: boto3 (==1.9.86)
